{

  "id": "4",

  "customer-id": "3",

  "items": [

    {

      "product-id": "A101",

      "quantity": "1",

      "unit-price": "9.75",

      "total": "9.75"

    },

    {

      "product-id": "A102",

      "quantity": "2",

      "unit-price": "49.50",

      "total": "99.00"

    },
    
    {

      "product-id": "B102",

      "quantity": "10",

      "unit-price": "4.99",

      "total": "49.90"

    },
    
    {

      "product-id": "B103",

      "quantity": "23",

      "unit-price": "12.95",

      "total": "297.85"

    }

  ],

  "total": "456.50"

}


